README.rst
setup.py
hug/__init__.py
hug/hug.py
mercurial_hug.egg-info/PKG-INFO
mercurial_hug.egg-info/SOURCES.txt
mercurial_hug.egg-info/dependency_links.txt
mercurial_hug.egg-info/requires.txt
mercurial_hug.egg-info/top_level.txt