Metadata-Version: 1.1
Name: mercurial-hug
Version: 0.4.1
Summary: A wrapper for select Mercurial functionality.
Home-page: https://goldman.ncodamusic.org/diffusion/10/
Author: Christopher Antila
Author-email: christopher@antila.ca
License: AGPLv3+
Keywords: mercurial,vcs,version control,wrapper
Platform: UNKNOWN
Classifier: Development Status :: 3 - Alpha
Classifier: Programming Language :: Python :: 2.7
Classifier: Programming Language :: Python :: Implementation :: CPython
Classifier: Programming Language :: Python :: Implementation :: PyPy
Classifier: Natural Language :: English
Classifier: Operating System :: OS Independent
